penaltymodel/__init__.py
penaltymodel/lp/__init__.py
penaltymodel/lp/generation.py
penaltymodel/lp/interface.py
penaltymodel/lp/package_info.py
penaltymodel_lp-0.1.6.dist-info/METADATA
penaltymodel_lp-0.1.6.dist-info/WHEEL
penaltymodel_lp-0.1.6.dist-info/entry_points.txt
penaltymodel_lp-0.1.6.dist-info/top_level.txt
penaltymodel_lp-0.1.6.dist-info/RECORD
