Metadata-Version: 2.1
Name: penaltymodel-lp
Version: 0.1.6
Summary: Generates penalty models using SciPy's linear programming.
Home-page: https://github.com/dwavesystems/penaltymodel
Author: D-Wave Systems Inc.
Author-email: mwong@dwavesys.com
License: Apache 2.0
Platform: UNKNOWN
Classifier: License :: OSI Approved :: Apache Software License
Classifier: Operating System :: MacOS :: MacOS X
Classifier: Operating System :: Microsoft :: Windows
Classifier: Operating System :: POSIX :: Linux
Classifier: Programming Language :: Python :: 3
Classifier: Programming Language :: Python :: 3.6
Classifier: Programming Language :: Python :: 3.7
Classifier: Programming Language :: Python :: 3.8
Classifier: Programming Language :: Python :: 3.9
Classifier: Programming Language :: Python :: 3.10
Requires-Python: >=3.6
Requires-Dist: dimod (<0.11.0,>=0.8.0)
Requires-Dist: penaltymodel (<0.17.0,>=0.16.0)
Requires-Dist: scipy (<2.0.0,>=1.5.2)
Requires-Dist: numpy (<2.0.0,>=1.19.1)
